crnt4sbml/__init__.py
crnt4sbml/advanced_deficiency_approach.py
crnt4sbml/bistability_analysis.py
crnt4sbml/bistability_finder.py
crnt4sbml/c_graph.py
crnt4sbml/crnt.py
crnt4sbml/general_approach.py
crnt4sbml/low_deficiency_approach.py
crnt4sbml/mass_conservation_approach.py
crnt4sbml/mpi_routines.py
crnt4sbml/safety_wrap.py
crnt4sbml/semi_diffusive_approach.py
crnt4sbml-0.0.15.dist-info/AUTHORS.rst
crnt4sbml-0.0.15.dist-info/LICENSE
crnt4sbml-0.0.15.dist-info/METADATA
crnt4sbml-0.0.15.dist-info/WHEEL
crnt4sbml-0.0.15.dist-info/entry_points.txt
crnt4sbml-0.0.15.dist-info/top_level.txt
crnt4sbml-0.0.15.dist-info/RECORD
