Metadata-Version: 2.1
Name: crnt4sbml
Version: 0.0.15
Summary: CRNT4SBML is an easily installable Python based package available on MacOS and Windows. CRNT4SBML is concentrated on providing a simple workflow for the testing of core CRNT methods directed at detecting bistability in cell signaling pathways endowed with mass action kinetics.
Home-page: https://github.com/PNNL-Comp-Mass-Spec/CRNT4SBML
Author: Brandon Reyes
Author-email: reyesb123@gmail.com
License: Apache Software License 2.0
Keywords: crnt4sbml
Platform: ALL
Classifier: Development Status :: 2 - Pre-Alpha
Classifier: Intended Audience :: Developers
Classifier: License :: OSI Approved :: Apache Software License
Classifier: Natural Language :: English
Classifier: Programming Language :: Python :: 3.7
Requires-Dist: networkx (==2.3)
Requires-Dist: python-libsbml (==5.18.0)
Requires-Dist: numpy (==1.16.4)
Requires-Dist: sympy (==1.4)
Requires-Dist: scipy (==1.4.1)
Requires-Dist: matplotlib (==3.1.1)
Requires-Dist: plotnine (==0.6.0)
Provides-Extra: linux
Provides-Extra: mpilinux
Requires-Dist: mpi4py (==3.0.3); extra == 'mpilinux'
Provides-Extra: mpimacos
Requires-Dist: antimony (==2.11.0); extra == 'mpimacos'
Requires-Dist: libroadrunner (==1.5.2.1); extra == 'mpimacos'
Requires-Dist: rrplugins (==1.2.2); extra == 'mpimacos'
Requires-Dist: mpi4py (==3.0.3); extra == 'mpimacos'
Provides-Extra: mpiwindows
Requires-Dist: antimony (==2.11.0); extra == 'mpiwindows'
Requires-Dist: libroadrunner (==1.5.2.1); extra == 'mpiwindows'
Requires-Dist: rrplugins (==1.2.2); extra == 'mpiwindows'
Requires-Dist: mpi4py (==3.0.3); extra == 'mpiwindows'
Provides-Extra: macos
Requires-Dist: antimony (==2.11.0); extra == 'macos'
Requires-Dist: libroadrunner (==1.5.2.1); extra == 'macos'
Requires-Dist: rrplugins (==1.2.2); extra == 'macos'
Provides-Extra: windows
Requires-Dist: antimony (==2.11.0); extra == 'windows'
Requires-Dist: libroadrunner (==1.5.2.1); extra == 'windows'
Requires-Dist: rrplugins (==1.2.2); extra == 'windows'
